README.md
setup.py
gdbp/__init__.py
gdbp/general.py
gdbp/rw_memory.py
gdbp/rw_registers.py
gdbp.egg-info/PKG-INFO
gdbp.egg-info/SOURCES.txt
gdbp.egg-info/dependency_links.txt
gdbp.egg-info/requires.txt
gdbp.egg-info/top_level.txt