Metadata-Version: 2.1
Name: gdbp
Version: 0.2.1
Summary: A wrapper for GDB's Python API
Home-page: https://github.com/ramikg/gdbp
License: UNKNOWN
Platform: UNKNOWN
Classifier: Programming Language :: Python :: 2
Classifier: Programming Language :: Python :: 3
Classifier: Operating System :: POSIX :: Linux
Provides-Extra: test
